./.buildnum
./.env.template
./.gitignore
./LICENSE
./PKG-INFO
./README.md
./__init__.py
./_version.py
./api.py
./pyproject.toml
./requirements.txt
./setup.py
./vendor-doc.md
./.github/workflows/codeql.yml
./.github/workflows/python-package.yml
./.github/workflows/python-publish.yml
./tests/__init__.py
./tests/test_api.py
aloha_api-0.2.0.dist-info/METADATA
aloha_api-0.2.0.dist-info/WHEEL
aloha_api-0.2.0.dist-info/licenses/LICENSE
aloha_api-0.2.0.dist-info/RECORD
