Metadata-Version: 2.4
Name: aloha_api
Version: 0.2.0
Summary: A Python client for the Aloha ABA Practice Management Software API
Author-email: Jordan Haisley <jordanhaisley@gmail.com>
License: MIT
License-File: LICENSE
Classifier: Development Status :: 4 - Beta
Classifier: Intended Audience :: Developers
Classifier: License :: OSI Approved :: MIT License
Classifier: Operating System :: OS Independent
Classifier: Programming Language :: Python :: 3
Classifier: Programming Language :: Python :: 3.8
Classifier: Programming Language :: Python :: 3.9
Classifier: Programming Language :: Python :: 3.10
Classifier: Programming Language :: Python :: 3.11
Classifier: Programming Language :: Python :: 3.12
Requires-Python: >=3.8
Requires-Dist: python-dotenv>=0.19.0
Requires-Dist: requests>=2.25.0
Requires-Dist: tomli>=2.0.0
